django_analyticsds/.DS_Store
django_analyticsds/__init__.py
django_analyticsds/admin.py
django_analyticsds/apps.py
django_analyticsds/models.py
django_analyticsds/tests.py
django_analyticsds/views.py
django_analyticsds/migrations/__init__.py
django_analyticsds/templates/django_analyticsds/analyticsds.html
django_analyticsds/templatetags/__init__.py
django_analyticsds/templatetags/django_analyticsds_tags.py
django_analyticsds-0.3.3.dist-info/LICENSE
django_analyticsds-0.3.3.dist-info/WHEEL
django_analyticsds-0.3.3.dist-info/METADATA
django_analyticsds-0.3.3.dist-info/RECORD
